BotAmino/Bot.py
BotAmino/BotAmino.py
BotAmino/__init__.py
BotAmino/commands.py
BotAmino/extensions.py
Dickbot.py-1.1.dist-info/METADATA
Dickbot.py-1.1.dist-info/WHEEL
Dickbot.py-1.1.dist-info/top_level.txt
Dickbot.py-1.1.dist-info/RECORD
