Metadata-Version: 2.1
Name: Dickbot.py
Version: 1.1
Summary: A library to create Amino bots.
Home-page: https://github.com/ThePhoenix78/AminoBot
Author: ThePhoenix78
Author-email: thephoenix788@gmail.com
License: MIT
Download-URL: https://github.com/ThePhoenix78/AminoBot/tarball/master
Keywords: aminoapps,amino-py,amino,amino-bot,narvii,api,python,python3,python3.x,ThePhoenix78,AminoBot,BotAmino,botamino,aminobot
Platform: UNKNOWN
Classifier: Programming Language :: Python :: 3
Classifier: License :: OSI Approved :: MIT License
Classifier: Operating System :: OS Independent
Requires-Dist: setuptools
Requires-Dist: requests
Requires-Dist: six
Requires-Dist: websocket-client
Requires-Dist: pathlib
Requires-Dist: Dick.py
